kids_video_bot.py
kids_video_bot-0.1.0.dist-info/METADATA
kids_video_bot-0.1.0.dist-info/WHEEL
kids_video_bot-0.1.0.dist-info/RECORD
