Metadata-Version: 2.1
Name: kids_video_bot
Version: 0.1.0
Summary: A Kids Video Builder Bot using AI
Author: Mathew Gomas
Author-email: mathewgomas@gmail.com
Requires-Python: >=3.12,<4.0
Classifier: Programming Language :: Python :: 3
Classifier: Programming Language :: Python :: 3.12
Requires-Dist: PyQt6 (>=6.7.1,<7.0.0)
Requires-Dist: openai (>=1.35.15,<2.0.0)
Requires-Dist: python-dotenv (>=1.0.0,<2.0.0)
